openrouteservice/__init__.py
openrouteservice/client.py
openrouteservice/convert.py
openrouteservice/deprecation.py
openrouteservice/directions.py
openrouteservice/distance_matrix.py
openrouteservice/elevation.py
openrouteservice/exceptions.py
openrouteservice/geocode.py
openrouteservice/isochrones.py
openrouteservice/optimization.py
openrouteservice/places.py
openrouteservice-2.3.3.dist-info/AUTHORS
openrouteservice-2.3.3.dist-info/LICENSE
openrouteservice-2.3.3.dist-info/METADATA
openrouteservice-2.3.3.dist-info/WHEEL
openrouteservice-2.3.3.dist-info/top_level.txt
openrouteservice-2.3.3.dist-info/RECORD
