Metadata-Version: 2.1
Name: openrouteservice
Version: 2.3.3
Summary: Python client for requests to openrouteservice API services
Home-page: https://github.com/GIScience/openrouteservice-py
Author: Nils Nolde
Author-email: nils.nolde@gmail.com
License: Apache-2.0
Keywords: routing accessibility router OSM ORS openrouteservice openstreetmap isochrone POI elevation DEM
Platform: UNKNOWN
Classifier: Development Status :: 4 - Beta
Classifier: License :: OSI Approved :: Apache Software License
Classifier: Operating System :: OS Independent
Classifier: Programming Language :: Python :: 2.7
Classifier: Programming Language :: Python :: 3.4
Classifier: Programming Language :: Python :: 3.5
Classifier: Programming Language :: Python :: 3.6
Classifier: Programming Language :: Python :: 3.7
Classifier: Programming Language :: Python :: Implementation :: CPython
Classifier: Programming Language :: Python :: Implementation :: PyPy
